deadline/maya_adaptor/__init__.py
deadline/maya_adaptor/_version.py
deadline/maya_adaptor/MayaAdaptor/MayaAdaptor.json
deadline/maya_adaptor/MayaAdaptor/__init__.py
deadline/maya_adaptor/MayaAdaptor/__main__.py
deadline/maya_adaptor/MayaAdaptor/adaptor.py
deadline/maya_adaptor/MayaAdaptor/py.typed
deadline/maya_adaptor/MayaAdaptor/schemas/init_data.schema.json
deadline/maya_adaptor/MayaAdaptor/schemas/run_data.schema.json
deadline/maya_adaptor/MayaClient/__init__.py
deadline/maya_adaptor/MayaClient/dir_map.py
deadline/maya_adaptor/MayaClient/maya_client.py
deadline/maya_adaptor/MayaClient/py.typed
deadline/maya_adaptor/MayaClient/render_handlers/__init__.py
deadline/maya_adaptor/MayaClient/render_handlers/arnold_handler.py
deadline/maya_adaptor/MayaClient/render_handlers/default_maya_handler.py
deadline/maya_adaptor/MayaClient/render_handlers/redshift_handler.py
deadline/maya_adaptor/MayaClient/render_handlers/renderman_handler.py
deadline/maya_adaptor/MayaClient/render_handlers/vray_handler.py
deadline/maya_submitter/__init__.py
deadline/maya_submitter/_version.py
deadline/maya_submitter/adaptor_override_environment.yaml
deadline/maya_submitter/assets.py
deadline/maya_submitter/cameras.py
deadline/maya_submitter/data_classes.py
deadline/maya_submitter/default_maya_job_template.yaml
deadline/maya_submitter/file_path_editor.py
deadline/maya_submitter/job_bundle_output_test_runner.py
deadline/maya_submitter/logging.py
deadline/maya_submitter/maya_render_submitter.py
deadline/maya_submitter/mel_commands.py
deadline/maya_submitter/render_layers.py
deadline/maya_submitter/renderers.py
deadline/maya_submitter/scene.py
deadline/maya_submitter/shelf.py
deadline/maya_submitter/utils.py
deadline/maya_submitter/ui/__init__.py
deadline/maya_submitter/ui/components/__init__.py
deadline/maya_submitter/ui/components/scene_settings_tab.py
deadline/maya_submitter/maya_submitter_plugin/DeadlineCloudForMaya.mod
deadline_cloud_for_maya-0.15.12.dist-info/METADATA
deadline_cloud_for_maya-0.15.12.dist-info/WHEEL
deadline_cloud_for_maya-0.15.12.dist-info/entry_points.txt
deadline_cloud_for_maya-0.15.12.dist-info/licenses/LICENSE
deadline_cloud_for_maya-0.15.12.dist-info/licenses/NOTICE
deadline_cloud_for_maya-0.15.12.dist-info/RECORD
