Metadata-Version: 2.4
Name: deadline-cloud-for-maya
Version: 0.15.12
Summary: AWS Deadline Cloud for Maya
Project-URL: Homepage, https://github.com/aws-deadline/deadline-cloud-for-maya
Project-URL: Source, https://github.com/aws-deadline/deadline-cloud-for-maya
Project-URL: Changelog, https://github.com/aws-deadline/deadline-cloud-for-maya/blob/release/CHANGELOG.md
Author: Amazon Web Services
License-Expression: Apache-2.0
License-File: LICENSE
License-File: NOTICE
Classifier: Development Status :: 5 - Production/Stable
Classifier: Intended Audience :: Developers
Classifier: Intended Audience :: End Users/Desktop
Classifier: License :: OSI Approved :: Apache Software License
Classifier: Operating System :: MacOS
Classifier: Operating System :: Microsoft :: Windows
Classifier: Operating System :: POSIX :: Linux
Classifier: Programming Language :: Python
Classifier: Programming Language :: Python :: 3 :: Only
Classifier: Programming Language :: Python :: 3.9
Classifier: Programming Language :: Python :: 3.10
Classifier: Programming Language :: Python :: 3.11
Classifier: Programming Language :: Python :: 3.12
Requires-Python: >=3.9
Requires-Dist: deadline==0.52.*
Requires-Dist: openjd-adaptor-runtime==0.9.*
